aws_cred_gen-0.0.7.dist-info/METADATA
aws_cred_gen-0.0.7.dist-info/RECORD
aws_cred_gen-0.0.7.dist-info/WHEEL
aws_cred_gen-0.0.7.dist-info/entry_points.txt
aws_cred_gen-0.0.7.dist-info/top_level.txt
aws_cred_generator/__init__.py
aws_cred_generator/cli.py
