Metadata-Version: 2.1
Name: aws-cred-gen
Version: 0.0.7
Summary: Package uses sts to assume a role based on AWS profile passed in
Home-page: UNKNOWN
Author: Zacharias Thompson
Author-email: UNKNOWN
License: MIT
Keywords: aws,credentials,aws sts
Platform: UNKNOWN
Classifier: Programming Language :: Python
Classifier: Programming Language :: Python :: 2.7
Requires-Dist: click
Requires-Dist: boto3
